django_native_search/__init__.py
django_native_search/admin.py
django_native_search/apps.py
django_native_search/fields.py
django_native_search/forms.py
django_native_search/manager.py
django_native_search/models.py
django_native_search/migrations/0001_initial.py
django_native_search/migrations/0002_index.py
django_native_search/migrations/__init__.py
django_native_search/migrations/operations/__init__.py
django_native_search-0.6.dist-info/LICENSE
django_native_search-0.6.dist-info/METADATA
django_native_search-0.6.dist-info/WHEEL
django_native_search-0.6.dist-info/top_level.txt
django_native_search-0.6.dist-info/RECORD
