Metadata-Version: 2.1
Name: django-native-search
Version: 0.6
Summary: A simple search engine using native django database backend.
Home-page: https://github.com/kmierzeje/django-native-search
Author: Kamil Mierzejewski
License: UNKNOWN
Platform: UNKNOWN
Classifier: Development Status :: 4 - Beta
Classifier: Environment :: Web Environment
Classifier: Framework :: Django
Classifier: Intended Audience :: Developers
Classifier: License :: OSI Approved :: BSD License
Classifier: Natural Language :: English
Classifier: Operating System :: OS Independent
Classifier: Programming Language :: Python :: 3.9
License-File: LICENSE
Requires-Dist: django (>=3.2)
Requires-Dist: django-expression-index (>=0.1.0)
